{
    "DIR": "/Users/rabshakeh/Desktop/test/",
    "folders": {
        "dirnames": {
            "9c59ee6125be1b058e8b0c4335a100ec470a74df": {
                "dirname": "/Users/rabshakeh/Desktop/test/",
                "dirnamehash": "9c59ee6125be1b058e8b0c4335a100ec470a74df",
                "filenames": [
                    {
                        "name": ".DS_Store"
                    }
                ],
                "nameshash": "4968ce20ca491441a8774eeaf1ba07bc3aa5105a"
            }
        },
        "filestats": {}
    },
    "numfiles": 5
}